{"stats":{"minecraft:killed":{"minecraft:skeleton":1,"minecraft:zombie":1},"minecraft:custom":{"minecraft:jump":6,"minecraft:time_since_rest":1067,"minecraft:leave_game":1,"minecraft:damage_dealt":400,"minecraft:damage_absorbed":24,"minecraft:sprint_one_cm":355,"minecraft:play_time":1067,"minecraft:damage_taken":32,"minecraft:time_since_death":1067,"minecraft:walk_one_cm":1584,"minecraft:sneak_time":8,"minecraft:total_world_time":1124,"minecraft:damage_resisted":6,"minecraft:mob_kills":2,"minecraft:fly_one_cm":3344},"minecraft:picked_up":{"minecraft:rotten_flesh":2},"minecraft:used":{"examplemod:fire_katana":4,"minecraft:enchanted_golden_apple":4}},"DataVersion":2975}